mose_framework/ConfigHandling.py
mose_framework/Organization.py
mose_framework/UserInterfaces.py
mose_framework/__init__.py
mose_framework-0.0.2.dist-info/LICENSE
mose_framework-0.0.2.dist-info/METADATA
mose_framework-0.0.2.dist-info/WHEEL
mose_framework-0.0.2.dist-info/top_level.txt
mose_framework-0.0.2.dist-info/RECORD
