Metadata-Version: 2.1
Name: mose-framework
Version: 0.0.2
Summary: Managing & Organizing Science Experiments
Author: Darik A. O'Neil
Author-email: d.oneil@columbia.edu
Maintainer-email: "Darik A. O'Neil" <d.oneil@columbia.edu>
License: GNU GENERAL PUBLIC LICENSE
Keywords: mose,test
Classifier: Development Status :: 2 - Pre-Alpha
Classifier: Programming Language :: Python
Requires-Python: <4,>=3.7
License-File: LICENSE
Requires-Dist: numpy
Requires-Dist: pandas
Requires-Dist: ipython
Requires-Dist: tqdm
